cedbox/__init__.py
cedbox/easymorse.py
cedbox/easystream.py
cedbox/easywav.py
cedbox/inputs.py
cedbox/yggdrasil.py
cedbox-0.1.4.dist-info/licenses/LICENSE
cedbox-0.1.4.dist-info/METADATA
cedbox-0.1.4.dist-info/WHEEL
cedbox-0.1.4.dist-info/top_level.txt
cedbox-0.1.4.dist-info/RECORD
