Metadata-Version: 2.4
Name: cedbox
Version: 0.1.4
Summary: A Python utility package for data handling, input validation, Morse code processing, and audio generation/streaming
Author-email: Cedric Sascha Wagner <cedric.sascha.wagner@outlook.de>
License: MIT License
Classifier: Programming Language :: Python :: 3
Classifier: Programming Language :: Python :: 3.10
Classifier: Programming Language :: Python :: 3.11
Classifier: Programming Language :: Python :: 3.12
Classifier: License :: OSI Approved :: MIT License
Classifier: Operating System :: OS Independent
Classifier: Topic :: Multimedia :: Sound/Audio
Classifier: Topic :: Utilities
Classifier: Intended Audience :: Developers
Classifier: Intended Audience :: Education
Requires-Python: >=3.10
License-File: LICENSE
Requires-Dist: pandas>=2.0.0
Requires-Dist: sounddevice>=0.5.2
Provides-Extra: dev
Requires-Dist: pytest>=7.0.0; extra == "dev"
Dynamic: license-file
